streamtools/__init__.py
streamtools/df/__init__.py
streamtools/df/streampepperdf.py
streamtools/df/streamspraydf.py
streamtools-0.1.dev2.dist-info/LICENSE
streamtools-0.1.dev2.dist-info/METADATA
streamtools-0.1.dev2.dist-info/WHEEL
streamtools-0.1.dev2.dist-info/top_level.txt
streamtools-0.1.dev2.dist-info/RECORD
