Metadata-Version: 2.1
Name: streamtools
Version: 0.1.dev2
Summary: Tools for modeling and analyzing stellar streams
Author: Jo Bovy
Author-email: bovy@astro.utoronto.ca
License: MIT
License-File: LICENSE
Requires-Dist: numpy (>=1.7)
Requires-Dist: scipy
Requires-Dist: galpy
